pylistmanager/__init__.py
pylistmanager/__main__.py
pylistmanager/__version__.py
pylistmanager/cli_movie.py
pylistmanager/common.py
pylistmanager/legoset.py
pylistmanager/listitem.py
pylistmanager/movie.py
pylistmanager-0.3.3.dist-info/LICENSE
pylistmanager-0.3.3.dist-info/METADATA
pylistmanager-0.3.3.dist-info/WHEEL
pylistmanager-0.3.3.dist-info/entry_points.txt
pylistmanager-0.3.3.dist-info/top_level.txt
pylistmanager-0.3.3.dist-info/RECORD
