Metadata-Version: 2.1
Name: pylistmanager
Version: 0.3.3
Summary: Manager for various kinds of lists.
Home-page: https://gitlab.com/sotirisp/pywatchlist
Author: Sotiris Papatheodorou
Author-email: sotirisp@protonmail.com
License: GPLv3
Platform: UNKNOWN
Classifier: Programming Language :: Python :: 3
Classifier: License :: OSI Approved :: GNU General Public License v3 (GPLv3)
Classifier: Intended Audience :: End Users/Desktop
Classifier: Environment :: Console
Classifier: Development Status :: 3 - Alpha
Requires-Python: >=3.5
Requires-Dist: xdg
Requires-Dist: colorama
